xscape/__init__.py
xscape/accessors.py
xscape/core.py
xscape/plotting.py
xscape/utils.py
xscape-0.3.0.dist-info/LICENSE
xscape-0.3.0.dist-info/METADATA
xscape-0.3.0.dist-info/WHEEL
xscape-0.3.0.dist-info/RECORD
