Metadata-Version: 2.3
Name: xscape
Version: 0.3.0
Summary: A Python library for recovering the seascape around a set of geographical points, based on Xarray.
License: GPL-3-or-later
Author: Articoking
Requires-Python: >=3.11
Classifier: License :: Other/Proprietary License
Classifier: Programming Language :: Python :: 3
Classifier: Programming Language :: Python :: 3.11
Classifier: Programming Language :: Python :: 3.12
Classifier: Programming Language :: Python :: 3.13
Requires-Dist: copernicusmarine (>=2.0.1,<3.0.0)
Requires-Dist: dask (>=2025.2.0,<2026.0.0)
Requires-Dist: netcdf4 (>=1.7.2,<2.0.0)
Requires-Dist: numpy (>=2.2.3,<3.0.0)
Requires-Dist: pandas (>=2.2.3,<3.0.0)
Requires-Dist: scipy (>=1.15.3,<2.0.0)
Requires-Dist: xarray (>=2025.1.2,<2026.0.0)
